{
  "0.05": {
    "1.00": {
      "b": 1.0,
      "H_star": 0.05,
      "f_BM": 0.6794907827747981,
      "A_BM": 0.25760461170033916,
      "G_BM": 0.17503995925066138,
      "BM_count": 0,
      "R_min": 1.65,
      "Rc_mean_kappa0": 3.9334208473215893,
      "Rc_mean_BM": 5.420143912099041,
      "Rmax_global": 33.588861641906,
      "kappa_definition": "R_min = kappa / mphi",
      "Rc_mean_kappa0_definition": "<Rc> over normalized p(Rc), i.e. kappa=0 / full-support mean",
      "Rc_mean_BM_definition": "<Rc> over the BM-selected support Rc >= R_min"
    },
    "2.00": {
      "b": 2.0,
      "H_star": 0.05,
      "f_BM": 0.6209147857683027,
      "A_BM": 0.27779113975768166,
      "G_BM": 0.17248462603097356,
      "BM_count": 0,
      "R_min": 1.65,
      "Rc_mean_kappa0": 3.337063432235654,
      "Rc_mean_BM": 4.906480870390798,
      "Rmax_global": 33.588861641906,
      "kappa_definition": "R_min = kappa / mphi",
      "Rc_mean_kappa0_definition": "<Rc> over normalized p(Rc), i.e. kappa=0 / full-support mean",
      "Rc_mean_BM_definition": "<Rc> over the BM-selected support Rc >= R_min"
    },
    "3.00": {
      "b": 3.0,
      "H_star": 0.05,
      "f_BM": 0.5621654923011211,
      "A_BM": 0.29730797223050986,
      "G_BM": 0.1671362825740126,
      "BM_count": 0,
      "R_min": 1.65,
      "Rc_mean_kappa0": 2.8364370749409953,
      "Rc_mean_BM": 4.460635350786878,
      "Rmax_global": 33.588861641906,
      "kappa_definition": "R_min = kappa / mphi",
      "Rc_mean_kappa0_definition": "<Rc> over normalized p(Rc), i.e. kappa=0 / full-support mean",
      "Rc_mean_BM_definition": "<Rc> over the BM-selected support Rc >= R_min"
    },
    "4.00": {
      "b": 4.0,
      "H_star": 0.05,
      "f_BM": 0.5060928111359967,
      "A_BM": 0.3153905562172538,
      "G_BM": 0.15961689320173558,
      "BM_count": 0,
      "R_min": 1.65,
      "Rc_mean_kappa0": 2.433706803946861,
      "Rc_mean_BM": 4.091035269920186,
      "Rmax_global": 33.588861641906,
      "kappa_definition": "R_min = kappa / mphi",
      "Rc_mean_kappa0_definition": "<Rc> over normalized p(Rc), i.e. kappa=0 / full-support mean",
      "Rc_mean_BM_definition": "<Rc> over the BM-selected support Rc >= R_min"
    },
    "5.00": {
      "b": 5.0,
      "H_star": 0.05,
      "f_BM": 0.4543238726430359,
      "A_BM": 0.33172550458189315,
      "G_BM": 0.15071081589611085,
      "BM_count": 0,
      "R_min": 1.65,
      "Rc_mean_kappa0": 2.1154675536864467,
      "Rc_mean_BM": 3.791396284077439,
      "Rmax_global": 33.588861641906,
      "kappa_definition": "R_min = kappa / mphi",
      "Rc_mean_kappa0_definition": "<Rc> over normalized p(Rc), i.e. kappa=0 / full-support mean",
      "Rc_mean_BM_definition": "<Rc> over the BM-selected support Rc >= R_min"
    },
    "6.00": {
      "b": 6.0,
      "H_star": 0.05,
      "f_BM": 0.4074773366979263,
      "A_BM": 0.3463018950314003,
      "G_BM": 0.14111017388083982,
      "BM_count": 0,
      "R_min": 1.65,
      "Rc_mean_kappa0": 1.8642326853327753,
      "Rc_mean_BM": 3.549880221518437,
      "Rmax_global": 33.588861641906,
      "kappa_definition": "R_min = kappa / mphi",
      "Rc_mean_kappa0_definition": "<Rc> over normalized p(Rc), i.e. kappa=0 / full-support mean",
      "Rc_mean_BM_definition": "<Rc> over the BM-selected support Rc >= R_min"
    },
    "8.00": {
      "b": 8.0,
      "H_star": 0.05,
      "f_BM": 0.32821415526158454,
      "A_BM": 0.3707998323960203,
      "G_BM": 0.12170175376099694,
      "BM_count": 0,
      "R_min": 1.65,
      "Rc_mean_kappa0": 1.5025552075815543,
      "Rc_mean_BM": 3.194465379801626,
      "Rmax_global": 33.588861641906,
      "kappa_definition": "R_min = kappa / mphi",
      "Rc_mean_kappa0_definition": "<Rc> over normalized p(Rc), i.e. kappa=0 / full-support mean",
      "Rc_mean_BM_definition": "<Rc> over the BM-selected support Rc >= R_min"
    },
    "10.00": {
      "b": 10.0,
      "H_star": 0.05,
      "f_BM": 0.26553801669795174,
      "A_BM": 0.39038662576058564,
      "G_BM": 0.10366249034987142,
      "BM_count": 0,
      "R_min": 1.65,
      "Rc_mean_kappa0": 1.2599019934430713,
      "Rc_mean_BM": 2.9511650366846216,
      "Rmax_global": 33.588861641906,
      "kappa_definition": "R_min = kappa / mphi",
      "Rc_mean_kappa0_definition": "<Rc> over normalized p(Rc), i.e. kappa=0 / full-support mean",
      "Rc_mean_BM_definition": "<Rc> over the BM-selected support Rc >= R_min"
    },
    "12.00": {
      "b": 12.0,
      "H_star": 0.05,
      "f_BM": 0.21591144783328117,
      "A_BM": 0.406381719130756,
      "G_BM": 0.08774246535049934,
      "BM_count": 0,
      "R_min": 1.65,
      "Rc_mean_kappa0": 1.0874663692358584,
      "Rc_mean_BM": 2.776140493023776,
      "Rmax_global": 33.588861641906,
      "kappa_definition": "R_min = kappa / mphi",
      "Rc_mean_kappa0_definition": "<Rc> over normalized p(Rc), i.e. kappa=0 / full-support mean",
      "Rc_mean_BM_definition": "<Rc> over the BM-selected support Rc >= R_min"
    },
    "16.00": {
      "b": 16.0,
      "H_star": 0.05,
      "f_BM": 0.14465988762577484,
      "A_BM": 0.4310734654440501,
      "G_BM": 0.062359039069589624,
      "BM_count": 0,
      "R_min": 1.65,
      "Rc_mean_kappa0": 0.8592490709843883,
      "Rc_mean_BM": 2.542109923326639,
      "Rmax_global": 33.588861641906,
      "kappa_definition": "R_min = kappa / mphi",
      "Rc_mean_kappa0_definition": "<Rc> over normalized p(Rc), i.e. kappa=0 / full-support mean",
      "Rc_mean_BM_definition": "<Rc> over the BM-selected support Rc >= R_min"
    },
    "20.00": {
      "b": 20.0,
      "H_star": 0.05,
      "f_BM": 0.09828253787259081,
      "A_BM": 0.44944417735615616,
      "G_BM": 0.04417251438262184,
      "BM_count": 0,
      "R_min": 1.65,
      "Rc_mean_kappa0": 0.7145756954516943,
      "Rc_mean_BM": 2.392499862230143,
      "Rmax_global": 33.588861641906,
      "kappa_definition": "R_min = kappa / mphi",
      "Rc_mean_kappa0_definition": "<Rc> over normalized p(Rc), i.e. kappa=0 / full-support mean",
      "Rc_mean_BM_definition": "<Rc> over the BM-selected support Rc >= R_min"
    },
    "25.00": {
      "b": 25.0,
      "H_star": 0.05,
      "f_BM": 0.061493687669432764,
      "A_BM": 0.4669215072464128,
      "G_BM": 0.028712725332751696,
      "BM_count": 0,
      "R_min": 1.65,
      "Rc_mean_kappa0": 0.593641303625761,
      "Rc_mean_BM": 2.2667422029863453,
      "Rmax_global": 33.588861641906,
      "kappa_definition": "R_min = kappa / mphi",
      "Rc_mean_kappa0_definition": "<Rc> over normalized p(Rc), i.e. kappa=0 / full-support mean",
      "Rc_mean_BM_definition": "<Rc> over the BM-selected support Rc >= R_min"
    },
    "32.00": {
      "b": 32.0,
      "H_star": 0.05,
      "f_BM": 0.03250065393337633,
      "A_BM": 0.4850519535986737,
      "G_BM": 0.015764505683618608,
      "BM_count": 0,
      "R_min": 1.65,
      "Rc_mean_kappa0": 0.4830109766321741,
      "Rc_mean_BM": 2.1511403044852373,
      "Rmax_global": 33.588861641906,
      "kappa_definition": "R_min = kappa / mphi",
      "Rc_mean_kappa0_definition": "<Rc> over normalized p(Rc), i.e. kappa=0 / full-support mean",
      "Rc_mean_BM_definition": "<Rc> over the BM-selected support Rc >= R_min"
    },
    "40.00": {
      "b": 40.0,
      "H_star": 0.05,
      "f_BM": 0.01597450240031997,
      "A_BM": 0.5002450808279751,
      "G_BM": 0.007991166244434746,
      "BM_count": 0,
      "R_min": 1.65,
      "Rc_mean_kappa0": 0.4004573111924074,
      "Rc_mean_BM": 2.0645047301736477,
      "Rmax_global": 33.588861641906,
      "kappa_definition": "R_min = kappa / mphi",
      "Rc_mean_kappa0_definition": "<Rc> over normalized p(Rc), i.e. kappa=0 / full-support mean",
      "Rc_mean_BM_definition": "<Rc> over the BM-selected support Rc >= R_min"
    }
  },
  "0.10": {
    "1.00": {
      "b": 1.0,
      "H_star": 0.1,
      "f_BM": 0.45538310673908233,
      "A_BM": 0.3450727249289711,
      "G_BM": 0.15714028952907566,
      "BM_count": 0,
      "R_min": 1.65,
      "Rc_mean_kappa0": 1.9715035745574947,
      "Rc_mean_BM": 3.452931861378854,
      "Rmax_global": 33.588861641906,
      "kappa_definition": "R_min = kappa / mphi",
      "Rc_mean_kappa0_definition": "<Rc> over normalized p(Rc), i.e. kappa=0 / full-support mean",
      "Rc_mean_BM_definition": "<Rc> over the BM-selected support Rc >= R_min"
    },
    "2.00": {
      "b": 2.0,
      "H_star": 0.1,
      "f_BM": 0.38296121589957377,
      "A_BM": 0.36274851586909296,
      "G_BM": 0.13891861270299366,
      "BM_count": 0,
      "R_min": 1.65,
      "Rc_mean_kappa0": 1.6735999121674723,
      "Rc_mean_BM": 3.2352706219949248,
      "Rmax_global": 33.588861641906,
      "kappa_definition": "R_min = kappa / mphi",
      "Rc_mean_kappa0_definition": "<Rc> over normalized p(Rc), i.e. kappa=0 / full-support mean",
      "Rc_mean_BM_definition": "<Rc> over the BM-selected support Rc >= R_min"
    },
    "3.00": {
      "b": 3.0,
      "H_star": 0.1,
      "f_BM": 0.3163356865397797,
      "A_BM": 0.37976789462863125,
      "G_BM": 0.12013413767311479,
      "BM_count": 0,
      "R_min": 1.65,
      "Rc_mean_kappa0": 1.4234658648857845,
      "Rc_mean_BM": 3.039959861194898,
      "Rmax_global": 33.588861641906,
      "kappa_definition": "R_min = kappa / mphi",
      "Rc_mean_kappa0_definition": "<Rc> over normalized p(Rc), i.e. kappa=0 / full-support mean",
      "Rc_mean_BM_definition": "<Rc> over the BM-selected support Rc >= R_min"
    },
    "4.00": {
      "b": 4.0,
      "H_star": 0.1,
      "f_BM": 0.2583962279238685,
      "A_BM": 0.3954351412381367,
      "G_BM": 0.10217894888447672,
      "BM_count": 0,
      "R_min": 1.65,
      "Rc_mean_kappa0": 1.2222066380390666,
      "Rc_mean_BM": 2.8731587025989382,
      "Rmax_global": 33.588861641906,
      "kappa_definition": "R_min = kappa / mphi",
      "Rc_mean_kappa0_definition": "<Rc> over normalized p(Rc), i.e. kappa=0 / full-support mean",
      "Rc_mean_BM_definition": "<Rc> over the BM-selected support Rc >= R_min"
    },
    "5.00": {
      "b": 5.0,
      "H_star": 0.1,
      "f_BM": 0.20986355850103486,
      "A_BM": 0.40947510281709437,
      "G_BM": 0.08593390219477255,
      "BM_count": 0,
      "R_min": 1.65,
      "Rc_mean_kappa0": 1.0631443989467881,
      "Rc_mean_BM": 2.734381475041522,
      "Rmax_global": 33.588861641906,
      "kappa_definition": "R_min = kappa / mphi",
      "Rc_mean_kappa0_definition": "<Rc> over normalized p(Rc), i.e. kappa=0 / full-support mean",
      "Rc_mean_BM_definition": "<Rc> over the BM-selected support Rc >= R_min"
    },
    "6.00": {
      "b": 6.0,
      "H_star": 0.1,
      "f_BM": 0.1701091755604463,
      "A_BM": 0.4218881883275098,
      "G_BM": 0.07176705189508299,
      "BM_count": 0,
      "R_min": 1.65,
      "Rc_mean_kappa0": 0.9375580110587018,
      "Rc_mean_BM": 2.620069719193712,
      "Rmax_global": 33.588861641906,
      "kappa_definition": "R_min = kappa / mphi",
      "Rc_mean_kappa0_definition": "<Rc> over normalized p(Rc), i.e. kappa=0 / full-support mean",
      "Rc_mean_BM_definition": "<Rc> over the BM-selected support Rc >= R_min"
    },
    "8.00": {
      "b": 8.0,
      "H_star": 0.1,
      "f_BM": 0.11200717548775027,
      "A_BM": 0.44243378655802834,
      "G_BM": 0.049555758772714925,
      "BM_count": 0,
      "R_min": 1.65,
      "Rc_mean_kappa0": 0.7567402074513115,
      "Rc_mean_BM": 2.4477730163367144,
      "Rmax_global": 33.588861641906,
      "kappa_definition": "R_min = kappa / mphi",
      "Rc_mean_kappa0_definition": "<Rc> over normalized p(Rc), i.e. kappa=0 / full-support mean",
      "Rc_mean_BM_definition": "<Rc> over the BM-selected support Rc >= R_min"
    },
    "10.00": {
      "b": 10.0,
      "H_star": 0.1,
      "f_BM": 0.07436726904404797,
      "A_BM": 0.45850864159432375,
      "G_BM": 0.03409803550846604,
      "BM_count": 0,
      "R_min": 1.65,
      "Rc_mean_kappa0": 0.6354166861336892,
      "Rc_mean_BM": 2.3270805558023113,
      "Rmax_global": 33.588861641906,
      "kappa_definition": "R_min = kappa / mphi",
      "Rc_mean_kappa0_definition": "<Rc> over normalized p(Rc), i.e. kappa=0 / full-support mean",
      "Rc_mean_BM_definition": "<Rc> over the BM-selected support Rc >= R_min"
    },
    "12.00": {
      "b": 12.0,
      "H_star": 0.1,
      "f_BM": 0.04985901528356383,
      "A_BM": 0.4713625326681431,
      "G_BM": 0.023501671720400304,
      "BM_count": 0,
      "R_min": 1.65,
      "Rc_mean_kappa0": 0.5491951270144818,
      "Rc_mean_BM": 2.238969945388688,
      "Rmax_global": 33.588861641906,
      "kappa_definition": "R_min = kappa / mphi",
      "Rc_mean_kappa0_definition": "<Rc> over normalized p(Rc), i.e. kappa=0 / full-support mean",
      "Rc_mean_BM_definition": "<Rc> over the BM-selected support Rc >= R_min"
    },
    "16.00": {
      "b": 16.0,
      "H_star": 0.1,
      "f_BM": 0.02300503396034734,
      "A_BM": 0.4906674883984694,
      "G_BM": 0.011287822233845123,
      "BM_count": 0,
      "R_min": 1.65,
      "Rc_mean_kappa0": 0.4350805873726584,
      "Rc_mean_BM": 2.119631167779868,
      "Rmax_global": 33.588861641906,
      "kappa_definition": "R_min = kappa / mphi",
      "Rc_mean_kappa0_definition": "<Rc> over normalized p(Rc), i.e. kappa=0 / full-support mean",
      "Rc_mean_BM_definition": "<Rc> over the BM-selected support Rc >= R_min"
    },
    "20.00": {
      "b": 20.0,
      "H_star": 0.1,
      "f_BM": 0.010911886233571583,
      "A_BM": 0.5045763831894836,
      "G_BM": 0.005505880089510666,
      "BM_count": 0,
      "R_min": 1.65,
      "Rc_mean_kappa0": 0.36274151354384404,
      "Rc_mean_BM": 2.0425179276985124,
      "Rmax_global": 33.588861641906,
      "kappa_definition": "R_min = kappa / mphi",
      "Rc_mean_kappa0_definition": "<Rc> over normalized p(Rc), i.e. kappa=0 / full-support mean",
      "Rc_mean_BM_definition": "<Rc> over the BM-selected support Rc >= R_min"
    },
    "25.00": {
      "b": 25.0,
      "H_star": 0.1,
      "f_BM": 0.004418983765105169,
      "A_BM": 0.5174325377508026,
      "G_BM": 0.002286525983857964,
      "BM_count": 0,
      "R_min": 1.65,
      "Rc_mean_kappa0": 0.30227583744712677,
      "Rc_mean_BM": 1.9772428769831514,
      "Rmax_global": 33.588861641906,
      "kappa_definition": "R_min = kappa / mphi",
      "Rc_mean_kappa0_definition": "<Rc> over normalized p(Rc), i.e. kappa=0 / full-support mean",
      "Rc_mean_BM_definition": "<Rc> over the BM-selected support Rc >= R_min"
    },
    "32.00": {
      "b": 32.0,
      "H_star": 0.1,
      "f_BM": 0.0012942301334009202,
      "A_BM": 0.5303718261666914,
      "G_BM": 0.0006864231993318067,
      "BM_count": 0,
      "R_min": 1.65,
      "Rc_mean_kappa0": 0.24696688646350545,
      "Rc_mean_BM": 1.9168799576316689,
      "Rmax_global": 33.588861641906,
      "kappa_definition": "R_min = kappa / mphi",
      "Rc_mean_kappa0_definition": "<Rc> over normalized p(Rc), i.e. kappa=0 / full-support mean",
      "Rc_mean_BM_definition": "<Rc> over the BM-selected support Rc >= R_min"
    },
    "40.00": {
      "b": 40.0,
      "H_star": 0.1,
      "f_BM": 0.0003300502264361991,
      "A_BM": 0.5408988952586271,
      "G_BM": 0.00017852380285919982,
      "BM_count": 0,
      "R_min": 1.65,
      "Rc_mean_kappa0": 0.2057028413105384,
      "Rc_mean_BM": 1.871409039316854,
      "Rmax_global": 33.588861641906,
      "kappa_definition": "R_min = kappa / mphi",
      "Rc_mean_kappa0_definition": "<Rc> over normalized p(Rc), i.e. kappa=0 / full-support mean",
      "Rc_mean_BM_definition": "<Rc> over the BM-selected support Rc >= R_min"
    }
  },
  "0.20": {
    "1.00": {
      "b": 1.0,
      "H_star": 0.2,
      "f_BM": 0.19410986509913897,
      "A_BM": 0.4354621921708527,
      "G_BM": 0.08452750737805954,
      "BM_count": 0,
      "R_min": 1.65,
      "Rc_mean_kappa0": 0.9905579933303065,
      "Rc_mean_BM": 2.461917482688291,
      "Rmax_global": 33.588861641906,
      "kappa_definition": "R_min = kappa / mphi",
      "Rc_mean_kappa0_definition": "<Rc> over normalized p(Rc), i.e. kappa=0 / full-support mean",
      "Rc_mean_BM_definition": "<Rc> over the BM-selected support Rc >= R_min"
    },
    "2.00": {
      "b": 2.0,
      "H_star": 0.2,
      "f_BM": 0.14116457779891464,
      "A_BM": 0.44643920392211167,
      "G_BM": 0.06302140173454845,
      "BM_count": 0,
      "R_min": 1.65,
      "Rc_mean_kappa0": 0.8418846831133991,
      "Rc_mean_BM": 2.387870593124024,
      "Rmax_global": 33.588861641906,
      "kappa_definition": "R_min = kappa / mphi",
      "Rc_mean_kappa0_definition": "<Rc> over normalized p(Rc), i.e. kappa=0 / full-support mean",
      "Rc_mean_BM_definition": "<Rc> over the BM-selected support Rc >= R_min"
    },
    "3.00": {
      "b": 3.0,
      "H_star": 0.2,
      "f_BM": 0.09926021596657224,
      "A_BM": 0.4573152968314942,
      "G_BM": 0.0453932151283112,
      "BM_count": 0,
      "R_min": 1.65,
      "Rc_mean_kappa0": 0.7170005510760169,
      "Rc_mean_BM": 2.3167763605216973,
      "Rmax_global": 33.588861641906,
      "kappa_definition": "R_min = kappa / mphi",
      "Rc_mean_kappa0_definition": "<Rc> over normalized p(Rc), i.e. kappa=0 / full-support mean",
      "Rc_mean_BM_definition": "<Rc> over the BM-selected support Rc >= R_min"
    },
    "4.00": {
      "b": 4.0,
      "H_star": 0.2,
      "f_BM": 0.06831196664980162,
      "A_BM": 0.4675372196682301,
      "G_BM": 0.031938386957517106,
      "BM_count": 0,
      "R_min": 1.65,
      "Rc_mean_kappa0": 0.6164791614940818,
      "Rc_mean_BM": 2.252420059818849,
      "Rmax_global": 33.588861641906,
      "kappa_definition": "R_min = kappa / mphi",
      "Rc_mean_kappa0_definition": "<Rc> over normalized p(Rc), i.e. kappa=0 / full-support mean",
      "Rc_mean_BM_definition": "<Rc> over the BM-selected support Rc >= R_min"
    },
    "5.00": {
      "b": 5.0,
      "H_star": 0.2,
      "f_BM": 0.046476411994026696,
      "A_BM": 0.47684430630153,
      "G_BM": 0.02216201243667577,
      "BM_count": 0,
      "R_min": 1.65,
      "Rc_mean_kappa0": 0.5370109907666096,
      "Rc_mean_BM": 2.1960691533902326,
      "Rmax_global": 33.588861641906,
      "kappa_definition": "R_min = kappa / mphi",
      "Rc_mean_kappa0_definition": "<Rc> over normalized p(Rc), i.e. kappa=0 / full-support mean",
      "Rc_mean_BM_definition": "<Rc> over the BM-selected support Rc >= R_min"
    },
    "6.00": {
      "b": 6.0,
      "H_star": 0.2,
      "f_BM": 0.03148051516080966,
      "A_BM": 0.4851690440564382,
      "G_BM": 0.015273371446974231,
      "BM_count": 0,
      "R_min": 1.65,
      "Rc_mean_kappa0": 0.4742516091897222,
      "Rc_mean_BM": 2.147570655052268,
      "Rmax_global": 33.588861641906,
      "kappa_definition": "R_min = kappa / mphi",
      "Rc_mean_kappa0_definition": "<Rc> over normalized p(Rc), i.e. kappa=0 / full-support mean",
      "Rc_mean_BM_definition": "<Rc> over the BM-selected support Rc >= R_min"
    },
    "8.00": {
      "b": 8.0,
      "H_star": 0.2,
      "f_BM": 0.014480508966511723,
      "A_BM": 0.49909452658029363,
      "G_BM": 0.0072271427672828655,
      "BM_count": 0,
      "R_min": 1.65,
      "Rc_mean_kappa0": 0.38387237240617206,
      "Rc_mean_BM": 2.0706203683089934,
      "Rmax_global": 33.588861641906,
      "kappa_definition": "R_min = kappa / mphi",
      "Rc_mean_kappa0_definition": "<Rc> over normalized p(Rc), i.e. kappa=0 / full-support mean",
      "Rc_mean_BM_definition": "<Rc> over the BM-selected support Rc >= R_min"
    },
    "10.00": {
      "b": 10.0,
      "H_star": 0.2,
      "f_BM": 0.006759648273064411,
      "A_BM": 0.5100565009249914,
      "G_BM": 0.0034478025456428944,
      "BM_count": 0,
      "R_min": 1.65,
      "Rc_mean_kappa0": 0.32322071972795335,
      "Rc_mean_BM": 2.013816525709058,
      "Rmax_global": 33.588861641906,
      "kappa_definition": "R_min = kappa / mphi",
      "Rc_mean_kappa0_definition": "<Rc> over normalized p(Rc), i.e. kappa=0 / full-support mean",
      "Rc_mean_BM_definition": "<Rc> over the BM-selected support Rc >= R_min"
    },
    "12.00": {
      "b": 12.0,
      "H_star": 0.2,
      "f_BM": 0.0032135135456682483,
      "A_BM": 0.5188231969839203,
      "G_BM": 0.0016672453713147337,
      "BM_count": 0,
      "R_min": 1.65,
      "Rc_mean_kappa0": 0.2801152240687646,
      "Rc_mean_BM": 1.9708050769566077,
      "Rmax_global": 33.588861641906,
      "kappa_definition": "R_min = kappa / mphi",
      "Rc_mean_kappa0_definition": "<Rc> over normalized p(Rc), i.e. kappa=0 / full-support mean",
      "Rc_mean_BM_definition": "<Rc> over the BM-selected support Rc >= R_min"
    },
    "16.00": {
      "b": 16.0,
      "H_star": 0.2,
      "f_BM": 0.0007636922704506122,
      "A_BM": 0.5319224097586277,
      "G_BM": 0.0004062250328121272,
      "BM_count": 0,
      "R_min": 1.65,
      "Rc_mean_kappa0": 0.223065352536131,
      "Rc_mean_BM": 1.9105162228063661,
      "Rmax_global": 33.588861641906,
      "kappa_definition": "R_min = kappa / mphi",
      "Rc_mean_kappa0_definition": "<Rc> over normalized p(Rc), i.e. kappa=0 / full-support mean",
      "Rc_mean_BM_definition": "<Rc> over the BM-selected support Rc >= R_min"
    },
    "20.00": {
      "b": 20.0,
      "H_star": 0.2,
      "f_BM": 0.0001915635409772469,
      "A_BM": 0.5412689129629606,
      "G_BM": 0.00010368738958808999,
      "BM_count": 0,
      "R_min": 1.65,
      "Rc_mean_kappa0": 0.18690669550776395,
      "Rc_mean_BM": 1.8703595154369603,
      "Rmax_global": 33.588861641906,
      "kappa_definition": "R_min = kappa / mphi",
      "Rc_mean_kappa0_definition": "<Rc> over normalized p(Rc), i.e. kappa=0 / full-support mean",
      "Rc_mean_BM_definition": "<Rc> over the BM-selected support Rc >= R_min"
    },
    "25.00": {
      "b": 25.0,
      "H_star": 0.2,
      "f_BM": 3.5969119936388174e-05,
      "A_BM": 0.5498149443534024,
      "G_BM": 1.9776359676266118e-05,
      "BM_count": 0,
      "R_min": 1.65,
      "Rc_mean_kappa0": 0.15669123994492562,
      "Rc_mean_BM": 1.8356621171231575,
      "Rmax_global": 33.588861641906,
      "kappa_definition": "R_min = kappa / mphi",
      "Rc_mean_kappa0_definition": "<Rc> over normalized p(Rc), i.e. kappa=0 / full-support mean",
      "Rc_mean_BM_definition": "<Rc> over the BM-selected support Rc >= R_min"
    },
    "32.00": {
      "b": 32.0,
      "H_star": 0.2,
      "f_BM": 3.727646247427228e-06,
      "A_BM": 0.5583125725742021,
      "G_BM": 2.0811917660476664e-06,
      "BM_count": 0,
      "R_min": 1.65,
      "Rc_mean_kappa0": 0.12906553380871372,
      "Rc_mean_BM": 1.8030066714675108,
      "Rmax_global": 33.588861641906,
      "kappa_definition": "R_min = kappa / mphi",
      "Rc_mean_kappa0_definition": "<Rc> over normalized p(Rc), i.e. kappa=0 / full-support mean",
      "Rc_mean_BM_definition": "<Rc> over the BM-selected support Rc >= R_min"
    },
    "40.00": {
      "b": 40.0,
      "H_star": 0.2,
      "f_BM": 3.009009655228351e-07,
      "A_BM": 0.5651431418342214,
      "G_BM": 1.7005211703652578e-07,
      "BM_count": 0,
      "R_min": 1.65,
      "Rc_mean_kappa0": 0.10847056265168956,
      "Rc_mean_BM": 1.7780401825070196,
      "Rmax_global": 33.588861641906,
      "kappa_definition": "R_min = kappa / mphi",
      "Rc_mean_kappa0_definition": "<Rc> over normalized p(Rc), i.e. kappa=0 / full-support mean",
      "Rc_mean_BM_definition": "<Rc> over the BM-selected support Rc >= R_min"
    }
  },
  "0.50": {
    "1.00": {
      "b": 1.0,
      "H_star": 0.5,
      "f_BM": 0.007053353897523673,
      "A_BM": 0.5450977701850013,
      "G_BM": 0.003844767481865842,
      "BM_count": 0,
      "R_min": 1.65,
      "Rc_mean_kappa0": 0.40202559520787023,
      "Rc_mean_BM": 1.8494184962821976,
      "Rmax_global": 33.588861641906,
      "kappa_definition": "R_min = kappa / mphi",
      "Rc_mean_kappa0_definition": "<Rc> over normalized p(Rc), i.e. kappa=0 / full-support mean",
      "Rc_mean_BM_definition": "<Rc> over the BM-selected support Rc >= R_min"
    },
    "2.00": {
      "b": 2.0,
      "H_star": 0.5,
      "f_BM": 0.0038940785724034806,
      "A_BM": 0.5462727585436232,
      "G_BM": 0.0021272290437324634,
      "BM_count": 0,
      "R_min": 1.65,
      "Rc_mean_kappa0": 0.34290406999744094,
      "Rc_mean_BM": 1.845139115507054,
      "Rmax_global": 33.588861641906,
      "kappa_definition": "R_min = kappa / mphi",
      "Rc_mean_kappa0_definition": "<Rc> over normalized p(Rc), i.e. kappa=0 / full-support mean",
      "Rc_mean_BM_definition": "<Rc> over the BM-selected support Rc >= R_min"
    },
    "3.00": {
      "b": 3.0,
      "H_star": 0.5,
      "f_BM": 0.001990614931339881,
      "A_BM": 0.547978897632065,
      "G_BM": 0.0010908149756855567,
      "BM_count": 0,
      "R_min": 1.65,
      "Rc_mean_kappa0": 0.29318088820025934,
      "Rc_mean_BM": 1.8388173304148225,
      "Rmax_global": 33.588861641906,
      "kappa_definition": "R_min = kappa / mphi",
      "Rc_mean_kappa0_definition": "<Rc> over normalized p(Rc), i.e. kappa=0 / full-support mean",
      "Rc_mean_BM_definition": "<Rc> over the BM-selected support Rc >= R_min"
    },
    "4.00": {
      "b": 4.0,
      "H_star": 0.5,
      "f_BM": 0.0009689260962094229,
      "A_BM": 0.5499052801849857,
      "G_BM": 0.0005328175764145872,
      "BM_count": 0,
      "R_min": 1.65,
      "Rc_mean_kappa0": 0.253117527859922,
      "Rc_mean_BM": 1.8316795935729473,
      "Rmax_global": 33.588861641906,
      "kappa_definition": "R_min = kappa / mphi",
      "Rc_mean_kappa0_definition": "<Rc> over normalized p(Rc), i.e. kappa=0 / full-support mean",
      "Rc_mean_BM_definition": "<Rc> over the BM-selected support Rc >= R_min"
    },
    "5.00": {
      "b": 5.0,
      "H_star": 0.5,
      "f_BM": 0.00045867746920518035,
      "A_BM": 0.5518938405573581,
      "G_BM": 0.00025314127005677633,
      "BM_count": 0,
      "R_min": 1.65,
      "Rc_mean_kappa0": 0.2214173666904927,
      "Rc_mean_BM": 1.8243446523623184,
      "Rmax_global": 33.588861641906,
      "kappa_definition": "R_min = kappa / mphi",
      "Rc_mean_kappa0_definition": "<Rc> over normalized p(Rc), i.e. kappa=0 / full-support mean",
      "Rc_mean_BM_definition": "<Rc> over the BM-selected support Rc >= R_min"
    },
    "6.00": {
      "b": 6.0,
      "H_star": 0.5,
      "f_BM": 0.00021443096747191683,
      "A_BM": 0.553846029548443,
      "G_BM": 0.00011876173994655247,
      "BM_count": 0,
      "R_min": 1.65,
      "Rc_mean_kappa0": 0.19636885371630125,
      "Rc_mean_BM": 1.8171883351619165,
      "Rmax_global": 33.588861641906,
      "kappa_definition": "R_min = kappa / mphi",
      "Rc_mean_kappa0_definition": "<Rc> over normalized p(Rc), i.e. kappa=0 / full-support mean",
      "Rc_mean_BM_definition": "<Rc> over the BM-selected support Rc >= R_min"
    },
    "8.00": {
      "b": 8.0,
      "H_star": 0.5,
      "f_BM": 4.6811590144754404e-05,
      "A_BM": 0.5574619046388894,
      "G_BM": 2.6095678201269856e-05,
      "BM_count": 0,
      "R_min": 1.65,
      "Rc_mean_kappa0": 0.1602775639634896,
      "Rc_mean_BM": 1.8040727944772361,
      "Rmax_global": 33.588861641906,
      "kappa_definition": "R_min = kappa / mphi",
      "Rc_mean_kappa0_definition": "<Rc> over normalized p(Rc), i.e. kappa=0 / full-support mean",
      "Rc_mean_BM_definition": "<Rc> over the BM-selected support Rc >= R_min"
    },
    "10.00": {
      "b": 10.0,
      "H_star": 0.5,
      "f_BM": 1.0500498198324464e-05,
      "A_BM": 0.5606055836585326,
      "G_BM": 5.8866379211770565e-06,
      "BM_count": 0,
      "R_min": 1.65,
      "Rc_mean_kappa0": 0.13605276809633282,
      "Rc_mean_BM": 1.792831856724984,
      "Rmax_global": 33.588861641906,
      "kappa_definition": "R_min = kappa / mphi",
      "Rc_mean_kappa0_definition": "<Rc> over normalized p(Rc), i.e. kappa=0 / full-support mean",
      "Rc_mean_BM_definition": "<Rc> over the BM-selected support Rc >= R_min"
    },
    "12.00": {
      "b": 12.0,
      "H_star": 0.5,
      "f_BM": 2.448207487200858e-06,
      "A_BM": 0.5633008747533742,
      "G_BM": 1.3790774191180035e-06,
      "BM_count": 0,
      "R_min": 1.65,
      "Rc_mean_kappa0": 0.11883881050759684,
      "Rc_mean_BM": 1.7833218765860486,
      "Rmax_global": 33.588861641906,
      "kappa_definition": "R_min = kappa / mphi",
      "Rc_mean_kappa0_definition": "<Rc> over normalized p(Rc), i.e. kappa=0 / full-support mean",
      "Rc_mean_BM_definition": "<Rc> over the BM-selected support Rc >= R_min"
    },
    "16.00": {
      "b": 16.0,
      "H_star": 0.5,
      "f_BM": 1.4917620755843778e-07,
      "A_BM": 0.5676192503765985,
      "G_BM": 8.467528710834432e-08,
      "BM_count": 0,
      "R_min": 1.65,
      "Rc_mean_kappa0": 0.09607411878895603,
      "Rc_mean_BM": 1.7683420310754292,
      "Rmax_global": 33.588861641906,
      "kappa_definition": "R_min = kappa / mphi",
      "Rc_mean_kappa0_definition": "<Rc> over normalized p(Rc), i.e. kappa=0 / full-support mean",
      "Rc_mean_BM_definition": "<Rc> over the BM-selected support Rc >= R_min"
    },
    "20.00": {
      "b": 20.0,
      "H_star": 0.5,
      "f_BM": 1.033565635340051e-08,
      "A_BM": 0.5709087943210033,
      "G_BM": 5.9007171072361026e-09,
      "BM_count": 0,
      "R_min": 1.65,
      "Rc_mean_kappa0": 0.08166608108611473,
      "Rc_mean_BM": 1.757150072435841,
      "Rmax_global": 33.588861641906,
      "kappa_definition": "R_min = kappa / mphi",
      "Rc_mean_kappa0_definition": "<Rc> over normalized p(Rc), i.e. kappa=0 / full-support mean",
      "Rc_mean_BM_definition": "<Rc> over the BM-selected support Rc >= R_min"
    },
    "25.00": {
      "b": 25.0,
      "H_star": 0.5,
      "f_BM": 4.219199059868329e-10,
      "A_BM": 0.5740709420435663,
      "G_BM": 2.422119578967941e-10,
      "BM_count": 0,
      "R_min": 1.65,
      "Rc_mean_kappa0": 0.0696534135221815,
      "Rc_mean_BM": 1.7465741589178507,
      "Rmax_global": 33.588861641906,
      "kappa_definition": "R_min = kappa / mphi",
      "Rc_mean_kappa0_definition": "<Rc> over normalized p(Rc), i.e. kappa=0 / full-support mean",
      "Rc_mean_BM_definition": "<Rc> over the BM-selected support Rc >= R_min"
    },
    "32.00": {
      "b": 32.0,
      "H_star": 0.5,
      "f_BM": 5.787750436951437e-12,
      "A_BM": 0.5773724138565631,
      "G_BM": 3.341687440582029e-12,
      "BM_count": 0,
      "R_min": 1.65,
      "Rc_mean_kappa0": 0.05870748348358708,
      "Rc_mean_BM": 1.735726259066885,
      "Rmax_global": 33.588861641906,
      "kappa_definition": "R_min = kappa / mphi",
      "Rc_mean_kappa0_definition": "<Rc> over normalized p(Rc), i.e. kappa=0 / full-support mean",
      "Rc_mean_BM_definition": "<Rc> over the BM-selected support Rc >= R_min"
    },
    "40.00": {
      "b": 40.0,
      "H_star": 0.5,
      "f_BM": 5.2065325155165837e-14,
      "A_BM": 0.5801559502571271,
      "G_BM": 3.020600819084154e-14,
      "BM_count": 0,
      "R_min": 1.65,
      "Rc_mean_kappa0": 0.05059039210649856,
      "Rc_mean_BM": 1.7267354342198493,
      "Rmax_global": 33.588861641906,
      "kappa_definition": "R_min = kappa / mphi",
      "Rc_mean_kappa0_definition": "<Rc> over normalized p(Rc), i.e. kappa=0 / full-support mean",
      "Rc_mean_BM_definition": "<Rc> over the BM-selected support Rc >= R_min"
    }
  },
  "1.00": {
    "1.00": {
      "b": 1.0,
      "H_star": 1.0,
      "f_BM": 0.0,
      "A_BM": 0.0,
      "G_BM": 0.0,
      "BM_count": 0,
      "R_min": 1.65,
      "Rc_mean_kappa0": 0.20590987999337168,
      "Rc_mean_BM": 0.0,
      "Rmax_global": 33.588861641906,
      "kappa_definition": "R_min = kappa / mphi",
      "Rc_mean_kappa0_definition": "<Rc> over normalized p(Rc), i.e. kappa=0 / full-support mean",
      "Rc_mean_BM_definition": "<Rc> over the BM-selected support Rc >= R_min"
    },
    "2.00": {
      "b": 2.0,
      "H_star": 1.0,
      "f_BM": 0.0,
      "A_BM": 0.0,
      "G_BM": 0.0,
      "BM_count": 0,
      "R_min": 1.65,
      "Rc_mean_kappa0": 0.17665731697500484,
      "Rc_mean_BM": 0.0,
      "Rmax_global": 33.588861641906,
      "kappa_definition": "R_min = kappa / mphi",
      "Rc_mean_kappa0_definition": "<Rc> over normalized p(Rc), i.e. kappa=0 / full-support mean",
      "Rc_mean_BM_definition": "<Rc> over the BM-selected support Rc >= R_min"
    },
    "3.00": {
      "b": 3.0,
      "H_star": 1.0,
      "f_BM": 0.0,
      "A_BM": 0.0,
      "G_BM": 0.0,
      "BM_count": 0,
      "R_min": 1.65,
      "Rc_mean_kappa0": 0.15200963871216697,
      "Rc_mean_BM": 0.0,
      "Rmax_global": 33.588861641906,
      "kappa_definition": "R_min = kappa / mphi",
      "Rc_mean_kappa0_definition": "<Rc> over normalized p(Rc), i.e. kappa=0 / full-support mean",
      "Rc_mean_BM_definition": "<Rc> over the BM-selected support Rc >= R_min"
    },
    "4.00": {
      "b": 4.0,
      "H_star": 1.0,
      "f_BM": 0.0,
      "A_BM": 0.0,
      "G_BM": 0.0,
      "BM_count": 0,
      "R_min": 1.65,
      "Rc_mean_kappa0": 0.1321201336488792,
      "Rc_mean_BM": 0.0,
      "Rmax_global": 33.588861641906,
      "kappa_definition": "R_min = kappa / mphi",
      "Rc_mean_kappa0_definition": "<Rc> over normalized p(Rc), i.e. kappa=0 / full-support mean",
      "Rc_mean_BM_definition": "<Rc> over the BM-selected support Rc >= R_min"
    },
    "5.00": {
      "b": 5.0,
      "H_star": 1.0,
      "f_BM": 0.0,
      "A_BM": 0.0,
      "G_BM": 0.0,
      "BM_count": 0,
      "R_min": 1.65,
      "Rc_mean_kappa0": 0.11636539867354921,
      "Rc_mean_BM": 0.0,
      "Rmax_global": 33.588861641906,
      "kappa_definition": "R_min = kappa / mphi",
      "Rc_mean_kappa0_definition": "<Rc> over normalized p(Rc), i.e. kappa=0 / full-support mean",
      "Rc_mean_BM_definition": "<Rc> over the BM-selected support Rc >= R_min"
    },
    "6.00": {
      "b": 6.0,
      "H_star": 1.0,
      "f_BM": 0.0,
      "A_BM": 0.0,
      "G_BM": 0.0,
      "BM_count": 0,
      "R_min": 1.65,
      "Rc_mean_kappa0": 0.10390779779664056,
      "Rc_mean_BM": 0.0,
      "Rmax_global": 33.588861641906,
      "kappa_definition": "R_min = kappa / mphi",
      "Rc_mean_kappa0_definition": "<Rc> over normalized p(Rc), i.e. kappa=0 / full-support mean",
      "Rc_mean_BM_definition": "<Rc> over the BM-selected support Rc >= R_min"
    },
    "8.00": {
      "b": 8.0,
      "H_star": 1.0,
      "f_BM": 0.0,
      "A_BM": 0.0,
      "G_BM": 0.0,
      "BM_count": 0,
      "R_min": 1.65,
      "Rc_mean_kappa0": 0.08595363565400682,
      "Rc_mean_BM": 0.0,
      "Rmax_global": 33.588861641906,
      "kappa_definition": "R_min = kappa / mphi",
      "Rc_mean_kappa0_definition": "<Rc> over normalized p(Rc), i.e. kappa=0 / full-support mean",
      "Rc_mean_BM_definition": "<Rc> over the BM-selected support Rc >= R_min"
    },
    "10.00": {
      "b": 10.0,
      "H_star": 1.0,
      "f_BM": 0.0,
      "A_BM": 0.0,
      "G_BM": 0.0,
      "BM_count": 0,
      "R_min": 1.65,
      "Rc_mean_kappa0": 0.07391096217713239,
      "Rc_mean_BM": 0.0,
      "Rmax_global": 33.588861641906,
      "kappa_definition": "R_min = kappa / mphi",
      "Rc_mean_kappa0_definition": "<Rc> over normalized p(Rc), i.e. kappa=0 / full-support mean",
      "Rc_mean_BM_definition": "<Rc> over the BM-selected support Rc >= R_min"
    },
    "12.00": {
      "b": 12.0,
      "H_star": 1.0,
      "f_BM": 0.0,
      "A_BM": 0.0,
      "G_BM": 0.0,
      "BM_count": 0,
      "R_min": 1.65,
      "Rc_mean_kappa0": 0.06536628239359646,
      "Rc_mean_BM": 0.0,
      "Rmax_global": 33.588861641906,
      "kappa_definition": "R_min = kappa / mphi",
      "Rc_mean_kappa0_definition": "<Rc> over normalized p(Rc), i.e. kappa=0 / full-support mean",
      "Rc_mean_BM_definition": "<Rc> over the BM-selected support Rc >= R_min"
    },
    "16.00": {
      "b": 16.0,
      "H_star": 1.0,
      "f_BM": 0.0,
      "A_BM": 0.0,
      "G_BM": 0.0,
      "BM_count": 0,
      "R_min": 1.65,
      "Rc_mean_kappa0": 0.0541011719788054,
      "Rc_mean_BM": 0.0,
      "Rmax_global": 33.588861641906,
      "kappa_definition": "R_min = kappa / mphi",
      "Rc_mean_kappa0_definition": "<Rc> over normalized p(Rc), i.e. kappa=0 / full-support mean",
      "Rc_mean_BM_definition": "<Rc> over the BM-selected support Rc >= R_min"
    },
    "20.00": {
      "b": 20.0,
      "H_star": 1.0,
      "f_BM": 0.0,
      "A_BM": 0.0,
      "G_BM": 0.0,
      "BM_count": 0,
      "R_min": 1.65,
      "Rc_mean_kappa0": 0.04701297593354399,
      "Rc_mean_BM": 0.0,
      "Rmax_global": 33.588861641906,
      "kappa_definition": "R_min = kappa / mphi",
      "Rc_mean_kappa0_definition": "<Rc> over normalized p(Rc), i.e. kappa=0 / full-support mean",
      "Rc_mean_BM_definition": "<Rc> over the BM-selected support Rc >= R_min"
    },
    "25.00": {
      "b": 25.0,
      "H_star": 1.0,
      "f_BM": 0.0,
      "A_BM": 0.0,
      "G_BM": 0.0,
      "BM_count": 0,
      "R_min": 1.65,
      "Rc_mean_kappa0": 0.041148845820468155,
      "Rc_mean_BM": 0.0,
      "Rmax_global": 33.588861641906,
      "kappa_definition": "R_min = kappa / mphi",
      "Rc_mean_kappa0_definition": "<Rc> over normalized p(Rc), i.e. kappa=0 / full-support mean",
      "Rc_mean_BM_definition": "<Rc> over the BM-selected support Rc >= R_min"
    },
    "32.00": {
      "b": 32.0,
      "H_star": 1.0,
      "f_BM": 0.0,
      "A_BM": 0.0,
      "G_BM": 0.0,
      "BM_count": 0,
      "R_min": 1.65,
      "Rc_mean_kappa0": 0.035871746483215124,
      "Rc_mean_BM": 0.0,
      "Rmax_global": 33.588861641906,
      "kappa_definition": "R_min = kappa / mphi",
      "Rc_mean_kappa0_definition": "<Rc> over normalized p(Rc), i.e. kappa=0 / full-support mean",
      "Rc_mean_BM_definition": "<Rc> over the BM-selected support Rc >= R_min"
    },
    "40.00": {
      "b": 40.0,
      "H_star": 1.0,
      "f_BM": 0.0,
      "A_BM": 0.0,
      "G_BM": 0.0,
      "BM_count": 0,
      "R_min": 1.65,
      "Rc_mean_kappa0": 0.032031003206486455,
      "Rc_mean_BM": 0.0,
      "Rmax_global": 33.588861641906,
      "kappa_definition": "R_min = kappa / mphi",
      "Rc_mean_kappa0_definition": "<Rc> over normalized p(Rc), i.e. kappa=0 / full-support mean",
      "Rc_mean_BM_definition": "<Rc> over the BM-selected support Rc >= R_min"
    }
  },
  "1.50": {
    "1.00": {
      "b": 1.0,
      "H_star": 1.5,
      "f_BM": 0.0,
      "A_BM": 0.0,
      "G_BM": 0.0,
      "BM_count": 0,
      "R_min": 1.65,
      "Rc_mean_kappa0": 0.1405904214267918,
      "Rc_mean_BM": 0.0,
      "Rmax_global": 33.588861641906,
      "kappa_definition": "R_min = kappa / mphi",
      "Rc_mean_kappa0_definition": "<Rc> over normalized p(Rc), i.e. kappa=0 / full-support mean",
      "Rc_mean_BM_definition": "<Rc> over the BM-selected support Rc >= R_min"
    },
    "2.00": {
      "b": 2.0,
      "H_star": 1.5,
      "f_BM": 0.0,
      "A_BM": 0.0,
      "G_BM": 0.0,
      "BM_count": 0,
      "R_min": 1.65,
      "Rc_mean_kappa0": 0.12130811525832211,
      "Rc_mean_BM": 0.0,
      "Rmax_global": 33.588861641906,
      "kappa_definition": "R_min = kappa / mphi",
      "Rc_mean_kappa0_definition": "<Rc> over normalized p(Rc), i.e. kappa=0 / full-support mean",
      "Rc_mean_BM_definition": "<Rc> over the BM-selected support Rc >= R_min"
    },
    "3.00": {
      "b": 3.0,
      "H_star": 1.5,
      "f_BM": 0.0,
      "A_BM": 0.0,
      "G_BM": 0.0,
      "BM_count": 0,
      "R_min": 1.65,
      "Rc_mean_kappa0": 0.10503604795844676,
      "Rc_mean_BM": 0.0,
      "Rmax_global": 33.588861641906,
      "kappa_definition": "R_min = kappa / mphi",
      "Rc_mean_kappa0_definition": "<Rc> over normalized p(Rc), i.e. kappa=0 / full-support mean",
      "Rc_mean_BM_definition": "<Rc> over the BM-selected support Rc >= R_min"
    },
    "4.00": {
      "b": 4.0,
      "H_star": 1.5,
      "f_BM": 0.0,
      "A_BM": 0.0,
      "G_BM": 0.0,
      "BM_count": 0,
      "R_min": 1.65,
      "Rc_mean_kappa0": 0.0918900246822843,
      "Rc_mean_BM": 0.0,
      "Rmax_global": 33.588861641906,
      "kappa_definition": "R_min = kappa / mphi",
      "Rc_mean_kappa0_definition": "<Rc> over normalized p(Rc), i.e. kappa=0 / full-support mean",
      "Rc_mean_BM_definition": "<Rc> over the BM-selected support Rc >= R_min"
    },
    "5.00": {
      "b": 5.0,
      "H_star": 1.5,
      "f_BM": 0.0,
      "A_BM": 0.0,
      "G_BM": 0.0,
      "BM_count": 0,
      "R_min": 1.65,
      "Rc_mean_kappa0": 0.08146790768790425,
      "Rc_mean_BM": 0.0,
      "Rmax_global": 33.588861641906,
      "kappa_definition": "R_min = kappa / mphi",
      "Rc_mean_kappa0_definition": "<Rc> over normalized p(Rc), i.e. kappa=0 / full-support mean",
      "Rc_mean_BM_definition": "<Rc> over the BM-selected support Rc >= R_min"
    },
    "6.00": {
      "b": 6.0,
      "H_star": 1.5,
      "f_BM": 0.0,
      "A_BM": 0.0,
      "G_BM": 0.0,
      "BM_count": 0,
      "R_min": 1.65,
      "Rc_mean_kappa0": 0.07322499722421913,
      "Rc_mean_BM": 0.0,
      "Rmax_global": 33.588861641906,
      "kappa_definition": "R_min = kappa / mphi",
      "Rc_mean_kappa0_definition": "<Rc> over normalized p(Rc), i.e. kappa=0 / full-support mean",
      "Rc_mean_BM_definition": "<Rc> over the BM-selected support Rc >= R_min"
    },
    "8.00": {
      "b": 8.0,
      "H_star": 1.5,
      "f_BM": 0.0,
      "A_BM": 0.0,
      "G_BM": 0.0,
      "BM_count": 0,
      "R_min": 1.65,
      "Rc_mean_kappa0": 0.061350544161936714,
      "Rc_mean_BM": 0.0,
      "Rmax_global": 33.588861641906,
      "kappa_definition": "R_min = kappa / mphi",
      "Rc_mean_kappa0_definition": "<Rc> over normalized p(Rc), i.e. kappa=0 / full-support mean",
      "Rc_mean_BM_definition": "<Rc> over the BM-selected support Rc >= R_min"
    },
    "10.00": {
      "b": 10.0,
      "H_star": 1.5,
      "f_BM": 0.0,
      "A_BM": 0.0,
      "G_BM": 0.0,
      "BM_count": 0,
      "R_min": 1.65,
      "Rc_mean_kappa0": 0.053399600691054115,
      "Rc_mean_BM": 0.0,
      "Rmax_global": 33.588861641906,
      "kappa_definition": "R_min = kappa / mphi",
      "Rc_mean_kappa0_definition": "<Rc> over normalized p(Rc), i.e. kappa=0 / full-support mean",
      "Rc_mean_BM_definition": "<Rc> over the BM-selected support Rc >= R_min"
    },
    "12.00": {
      "b": 12.0,
      "H_star": 1.5,
      "f_BM": 0.0,
      "A_BM": 0.0,
      "G_BM": 0.0,
      "BM_count": 0,
      "R_min": 1.65,
      "Rc_mean_kappa0": 0.04777454280960437,
      "Rc_mean_BM": 0.0,
      "Rmax_global": 33.588861641906,
      "kappa_definition": "R_min = kappa / mphi",
      "Rc_mean_kappa0_definition": "<Rc> over normalized p(Rc), i.e. kappa=0 / full-support mean",
      "Rc_mean_BM_definition": "<Rc> over the BM-selected support Rc >= R_min"
    },
    "16.00": {
      "b": 16.0,
      "H_star": 1.5,
      "f_BM": 0.0,
      "A_BM": 0.0,
      "G_BM": 0.0,
      "BM_count": 0,
      "R_min": 1.65,
      "Rc_mean_kappa0": 0.040400528507652245,
      "Rc_mean_BM": 0.0,
      "Rmax_global": 33.588861641906,
      "kappa_definition": "R_min = kappa / mphi",
      "Rc_mean_kappa0_definition": "<Rc> over normalized p(Rc), i.e. kappa=0 / full-support mean",
      "Rc_mean_BM_definition": "<Rc> over the BM-selected support Rc >= R_min"
    },
    "20.00": {
      "b": 20.0,
      "H_star": 1.5,
      "f_BM": 0.0,
      "A_BM": 0.0,
      "G_BM": 0.0,
      "BM_count": 0,
      "R_min": 1.65,
      "Rc_mean_kappa0": 0.03580439162915464,
      "Rc_mean_BM": 0.0,
      "Rmax_global": 33.588861641906,
      "kappa_definition": "R_min = kappa / mphi",
      "Rc_mean_kappa0_definition": "<Rc> over normalized p(Rc), i.e. kappa=0 / full-support mean",
      "Rc_mean_BM_definition": "<Rc> over the BM-selected support Rc >= R_min"
    },
    "25.00": {
      "b": 25.0,
      "H_star": 1.5,
      "f_BM": 0.0,
      "A_BM": 0.0,
      "G_BM": 0.0,
      "BM_count": 0,
      "R_min": 1.65,
      "Rc_mean_kappa0": 0.03205059024168577,
      "Rc_mean_BM": 0.0,
      "Rmax_global": 33.588861641906,
      "kappa_definition": "R_min = kappa / mphi",
      "Rc_mean_kappa0_definition": "<Rc> over normalized p(Rc), i.e. kappa=0 / full-support mean",
      "Rc_mean_BM_definition": "<Rc> over the BM-selected support Rc >= R_min"
    },
    "32.00": {
      "b": 32.0,
      "H_star": 1.5,
      "f_BM": 0.0,
      "A_BM": 0.0,
      "G_BM": 0.0,
      "BM_count": 0,
      "R_min": 1.65,
      "Rc_mean_kappa0": 0.028739125162395865,
      "Rc_mean_BM": 0.0,
      "Rmax_global": 33.588861641906,
      "kappa_definition": "R_min = kappa / mphi",
      "Rc_mean_kappa0_definition": "<Rc> over normalized p(Rc), i.e. kappa=0 / full-support mean",
      "Rc_mean_BM_definition": "<Rc> over the BM-selected support Rc >= R_min"
    },
    "40.00": {
      "b": 40.0,
      "H_star": 1.5,
      "f_BM": 0.0,
      "A_BM": 0.0,
      "G_BM": 0.0,
      "BM_count": 0,
      "R_min": 1.65,
      "Rc_mean_kappa0": 0.026399691490429818,
      "Rc_mean_BM": 0.0,
      "Rmax_global": 33.588861641906,
      "kappa_definition": "R_min = kappa / mphi",
      "Rc_mean_kappa0_definition": "<Rc> over normalized p(Rc), i.e. kappa=0 / full-support mean",
      "Rc_mean_BM_definition": "<Rc> over the BM-selected support Rc >= R_min"
    }
  },
  "2.00": {
    "1.00": {
      "b": 1.0,
      "H_star": 2.0,
      "f_BM": 0.0,
      "A_BM": 0.0,
      "G_BM": 0.0,
      "BM_count": 0,
      "R_min": 1.65,
      "Rc_mean_kappa0": 0.10796823673552955,
      "Rc_mean_BM": 0.0,
      "Rmax_global": 33.588861641906,
      "kappa_definition": "R_min = kappa / mphi",
      "Rc_mean_kappa0_definition": "<Rc> over normalized p(Rc), i.e. kappa=0 / full-support mean",
      "Rc_mean_BM_definition": "<Rc> over the BM-selected support Rc >= R_min"
    },
    "2.00": {
      "b": 2.0,
      "H_star": 2.0,
      "f_BM": 0.0,
      "A_BM": 0.0,
      "G_BM": 0.0,
      "BM_count": 0,
      "R_min": 1.65,
      "Rc_mean_kappa0": 0.0936840138175324,
      "Rc_mean_BM": 0.0,
      "Rmax_global": 33.588861641906,
      "kappa_definition": "R_min = kappa / mphi",
      "Rc_mean_kappa0_definition": "<Rc> over normalized p(Rc), i.e. kappa=0 / full-support mean",
      "Rc_mean_BM_definition": "<Rc> over the BM-selected support Rc >= R_min"
    },
    "3.00": {
      "b": 3.0,
      "H_star": 2.0,
      "f_BM": 0.0,
      "A_BM": 0.0,
      "G_BM": 0.0,
      "BM_count": 0,
      "R_min": 1.65,
      "Rc_mean_kappa0": 0.08161289796716109,
      "Rc_mean_BM": 0.0,
      "Rmax_global": 33.588861641906,
      "kappa_definition": "R_min = kappa / mphi",
      "Rc_mean_kappa0_definition": "<Rc> over normalized p(Rc), i.e. kappa=0 / full-support mean",
      "Rc_mean_BM_definition": "<Rc> over the BM-selected support Rc >= R_min"
    },
    "4.00": {
      "b": 4.0,
      "H_star": 2.0,
      "f_BM": 0.0,
      "A_BM": 0.0,
      "G_BM": 0.0,
      "BM_count": 0,
      "R_min": 1.65,
      "Rc_mean_kappa0": 0.07185004614638346,
      "Rc_mean_BM": 0.0,
      "Rmax_global": 33.588861641906,
      "kappa_definition": "R_min = kappa / mphi",
      "Rc_mean_kappa0_definition": "<Rc> over normalized p(Rc), i.e. kappa=0 / full-support mean",
      "Rc_mean_BM_definition": "<Rc> over the BM-selected support Rc >= R_min"
    },
    "5.00": {
      "b": 5.0,
      "H_star": 2.0,
      "f_BM": 0.0,
      "A_BM": 0.0,
      "G_BM": 0.0,
      "BM_count": 0,
      "R_min": 1.65,
      "Rc_mean_kappa0": 0.06410792856385704,
      "Rc_mean_BM": 0.0,
      "Rmax_global": 33.588861641906,
      "kappa_definition": "R_min = kappa / mphi",
      "Rc_mean_kappa0_definition": "<Rc> over normalized p(Rc), i.e. kappa=0 / full-support mean",
      "Rc_mean_BM_definition": "<Rc> over the BM-selected support Rc >= R_min"
    },
    "6.00": {
      "b": 6.0,
      "H_star": 2.0,
      "f_BM": 0.0,
      "A_BM": 0.0,
      "G_BM": 0.0,
      "BM_count": 0,
      "R_min": 1.65,
      "Rc_mean_kappa0": 0.05798484874646683,
      "Rc_mean_BM": 0.0,
      "Rmax_global": 33.588861641906,
      "kappa_definition": "R_min = kappa / mphi",
      "Rc_mean_kappa0_definition": "<Rc> over normalized p(Rc), i.e. kappa=0 / full-support mean",
      "Rc_mean_BM_definition": "<Rc> over the BM-selected support Rc >= R_min"
    },
    "8.00": {
      "b": 8.0,
      "H_star": 2.0,
      "f_BM": 0.0,
      "A_BM": 0.0,
      "G_BM": 0.0,
      "BM_count": 0,
      "R_min": 1.65,
      "Rc_mean_kappa0": 0.0491739054647863,
      "Rc_mean_BM": 0.0,
      "Rmax_global": 33.588861641906,
      "kappa_definition": "R_min = kappa / mphi",
      "Rc_mean_kappa0_definition": "<Rc> over normalized p(Rc), i.e. kappa=0 / full-support mean",
      "Rc_mean_BM_definition": "<Rc> over the BM-selected support Rc >= R_min"
    },
    "10.00": {
      "b": 10.0,
      "H_star": 2.0,
      "f_BM": 0.0,
      "A_BM": 0.0,
      "G_BM": 0.0,
      "BM_count": 0,
      "R_min": 1.65,
      "Rc_mean_kappa0": 0.0432920868817519,
      "Rc_mean_BM": 0.0,
      "Rmax_global": 33.588861641906,
      "kappa_definition": "R_min = kappa / mphi",
      "Rc_mean_kappa0_definition": "<Rc> over normalized p(Rc), i.e. kappa=0 / full-support mean",
      "Rc_mean_BM_definition": "<Rc> over the BM-selected support Rc >= R_min"
    },
    "12.00": {
      "b": 12.0,
      "H_star": 2.0,
      "f_BM": 0.0,
      "A_BM": 0.0,
      "G_BM": 0.0,
      "BM_count": 0,
      "R_min": 1.65,
      "Rc_mean_kappa0": 0.039148373063072124,
      "Rc_mean_BM": 0.0,
      "Rmax_global": 33.588861641906,
      "kappa_definition": "R_min = kappa / mphi",
      "Rc_mean_kappa0_definition": "<Rc> over normalized p(Rc), i.e. kappa=0 / full-support mean",
      "Rc_mean_BM_definition": "<Rc> over the BM-selected support Rc >= R_min"
    },
    "16.00": {
      "b": 16.0,
      "H_star": 2.0,
      "f_BM": 0.0,
      "A_BM": 0.0,
      "G_BM": 0.0,
      "BM_count": 0,
      "R_min": 1.65,
      "Rc_mean_kappa0": 0.03375757480544233,
      "Rc_mean_BM": 0.0,
      "Rmax_global": 33.588861641906,
      "kappa_definition": "R_min = kappa / mphi",
      "Rc_mean_kappa0_definition": "<Rc> over normalized p(Rc), i.e. kappa=0 / full-support mean",
      "Rc_mean_BM_definition": "<Rc> over the BM-selected support Rc >= R_min"
    },
    "20.00": {
      "b": 20.0,
      "H_star": 2.0,
      "f_BM": 0.0,
      "A_BM": 0.0,
      "G_BM": 0.0,
      "BM_count": 0,
      "R_min": 1.65,
      "Rc_mean_kappa0": 0.030441582426428783,
      "Rc_mean_BM": 0.0,
      "Rmax_global": 33.588861641906,
      "kappa_definition": "R_min = kappa / mphi",
      "Rc_mean_kappa0_definition": "<Rc> over normalized p(Rc), i.e. kappa=0 / full-support mean",
      "Rc_mean_BM_definition": "<Rc> over the BM-selected support Rc >= R_min"
    },
    "25.00": {
      "b": 25.0,
      "H_star": 2.0,
      "f_BM": 0.0,
      "A_BM": 0.0,
      "G_BM": 0.0,
      "BM_count": 0,
      "R_min": 1.65,
      "Rc_mean_kappa0": 0.027779456518293416,
      "Rc_mean_BM": 0.0,
      "Rmax_global": 33.588861641906,
      "kappa_definition": "R_min = kappa / mphi",
      "Rc_mean_kappa0_definition": "<Rc> over normalized p(Rc), i.e. kappa=0 / full-support mean",
      "Rc_mean_BM_definition": "<Rc> over the BM-selected support Rc >= R_min"
    },
    "32.00": {
      "b": 32.0,
      "H_star": 2.0,
      "f_BM": 0.0,
      "A_BM": 0.0,
      "G_BM": 0.0,
      "BM_count": 0,
      "R_min": 1.65,
      "Rc_mean_kappa0": 0.025492585754356218,
      "Rc_mean_BM": 0.0,
      "Rmax_global": 33.588861641906,
      "kappa_definition": "R_min = kappa / mphi",
      "Rc_mean_kappa0_definition": "<Rc> over normalized p(Rc), i.e. kappa=0 / full-support mean",
      "Rc_mean_BM_definition": "<Rc> over the BM-selected support Rc >= R_min"
    },
    "40.00": {
      "b": 40.0,
      "H_star": 2.0,
      "f_BM": 0.0,
      "A_BM": 0.0,
      "G_BM": 0.0,
      "BM_count": 0,
      "R_min": 1.65,
      "Rc_mean_kappa0": 0.023938231188923378,
      "Rc_mean_BM": 0.0,
      "Rmax_global": 33.588861641906,
      "kappa_definition": "R_min = kappa / mphi",
      "Rc_mean_kappa0_definition": "<Rc> over normalized p(Rc), i.e. kappa=0 / full-support mean",
      "Rc_mean_BM_definition": "<Rc> over the BM-selected support Rc >= R_min"
    }
  }
}